{
  "version": "2.0.0",
  "scrollSpeed": {
    "hard": 2.5,
    "normal": 1
  },
  "events": [
    {
      "t": 0,
      "e": "FocusCamera",
      "v": {
	"x": 0,
	"duration": 4,
	"y": 0,
	"ease": "CLASSIC",
	"char": 1
}
    },
    {
      "t": 6000,
      "e": "FocusCamera",
      "v": {
	"x": 0,
	"duration": 4,
	"y": 0,
	"ease": "CLASSIC",
	"char": 0
}
    },
    {
      "t": 18000,
      "e": "FocusCamera",
      "v": {
	"x": 0,
	"duration": 4,
	"y": 0,
	"ease": "CLASSIC",
	"char": 0
}
    },
    {
      "t": 24187.5,
      "e": "FocusCamera",
      "v": {
	"x": 0,
	"duration": 4,
	"y": 0,
	"ease": "CLASSIC",
	"char": 1
}
    },
    {
      "t": 27187.5,
      "e": "FocusCamera",
      "v": {
	"x": 0,
	"duration": 4,
	"y": 0,
	"ease": "CLASSIC",
	"char": 0
}
    },
    {
      "t": 30000,
      "e": "FocusCamera",
      "v": {
	"x": 0,
	"duration": 4,
	"y": 0,
	"ease": "CLASSIC",
	"char": 2
}
    },
    {
      "t": 30000,
      "e": "ZoomCamera",
      "v": {
	"ease": "cubeOut",
	"duration": 4,
	"zoom": 0.85,
	"mode": "stage"
}
    },
    {
      "t": 42000,
      "e": "FocusCamera",
      "v": {
	"x": 0,
	"duration": 4,
	"y": 0,
	"ease": "CLASSIC",
	"char": 1
}
    },
    {
      "t": 48000,
      "e": "FocusCamera",
      "v": {
	"x": 0,
	"duration": 4,
	"y": 0,
	"ease": "CLASSIC",
	"char": 0
}
    },
    {
      "t": 54000,
      "e": "FocusCamera",
      "v": {
	"x": 0,
	"duration": 4,
	"y": 0,
	"ease": "CLASSIC",
	"char": 1
}
    }
  ],
  "notes": {
    "easy": [    ],
    "normal": [    ],
    "hard": [
      {
        "t": 0,
        "d": 4,
        "l": 0,
        "p": {}
      },
      {
        "t": 187.5,
        "d": 5,
        "l": 0,
        "p": {}
      },
      {
        "t": 375,
        "d": 7,
        "l": 0,
        "p": {}
      },
      {
        "t": 562.5,
        "d": 6,
        "l": 187.5,
        "p": {}
      },
      {
        "t": 937.5,
        "d": 6,
        "l": 0,
        "p": {}
      },
      {
        "t": 1125,
        "d": 7,
        "l": 0,
        "p": {}
      },
      {
        "t": 1312.5,
        "d": 5,
        "l": 0,
        "p": {}
      },
      {
        "t": 1500,
        "d": 4,
        "l": 0,
        "p": {}
      },
      {
        "t": 1687.5,
        "d": 7,
        "l": 0,
        "p": {}
      },
      {
        "t": 1875,
        "d": 4,
        "l": 0,
        "p": {}
      },
      {
        "t": 2062.5,
        "d": 6,
        "l": 187.5,
        "p": {}
      },
      {
        "t": 2062.5,
        "d": 7,
        "l": 0,
        "p": {}
      },
      {
        "t": 2343.75,
        "d": 4,
        "l": 0,
        "p": {}
      },
      {
        "t": 2625,
        "d": 5,
        "l": 281.25,
        "p": {}
      },
      {
        "t": 3000,
        "d": 4,
        "l": 0,
        "p": {}
      },
      {
        "t": 3187.5,
        "d": 5,
        "l": 0,
        "p": {}
      },
      {
        "t": 3375,
        "d": 7,
        "l": 0,
        "p": {}
      },
      {
        "t": 3562.5,
        "d": 6,
        "l": 281.25,
        "p": {}
      },
      {
        "t": 3562.5,
        "d": 4,
        "l": 0,
        "p": {}
      },
      {
        "t": 3937.5,
        "d": 5,
        "l": 0,
        "p": {}
      },
      {
        "t": 4125,
        "d": 7,
        "l": 0,
        "p": {}
      },
      {
        "t": 4312.5,
        "d": 4,
        "l": 0,
        "p": {}
      },
      {
        "t": 4500,
        "d": 7,
        "l": 0,
        "p": {}
      },
      {
        "t": 4687.5,
        "d": 5,
        "l": 0,
        "p": {}
      },
      {
        "t": 4875,
        "d": 6,
        "l": 0,
        "p": {}
      },
      {
        "t": 5062.5,
        "d": 5,
        "l": 0,
        "p": {}
      },
      {
        "t": 5062.5,
        "d": 4,
        "l": 281.25,
        "p": {}
      },
      {
        "t": 5437.5,
        "d": 6,
        "l": 0,
        "p": {}
      },
      {
        "t": 5531.25,
        "d": 5,
        "l": 0,
        "p": {}
      },
      {
        "t": 5625,
        "d": 7,
        "l": 0,
        "p": {}
      },
      {
        "t": 5812.5,
        "d": 5,
        "l": 0,
        "p": {}
      },
      {
        "t": 6000,
        "d": 4,
        "l": 0,
        "p": {}
      },
      {
        "t": 6000,
        "d": 6,
        "l": 656.25,
        "p": {}
      },
      {
        "t": 6000,
        "d": 0,
        "l": 0,
        "p": {}
      },
      {
        "t": 6187.5,
        "d": 1,
        "l": 0
      },
      {
        "t": 6375,
        "d": 3,
        "l": 0
      },
      {
        "t": 6562.5,
        "d": 2,
        "l": 187.5
      },
      {
        "t": 6937.5,
        "d": 2,
        "l": 0
      },
      {
        "t": 7125,
        "d": 3,
        "l": 0
      },
      {
        "t": 7312.5,
        "d": 0,
        "l": 0
      },
      {
        "t": 7500,
        "d": 1,
        "l": 0
      },
      {
        "t": 7687.5,
        "d": 3,
        "l": 0
      },
      {
        "t": 7875,
        "d": 1,
        "l": 0
      },
      {
        "t": 8062.5,
        "d": 2,
        "l": 187.5
      },
      {
        "t": 8062.5,
        "d": 3,
        "l": 0,
        "p": {}
      },
      {
        "t": 8343.75,
        "d": 0,
        "l": 0
      },
      {
        "t": 8625,
        "d": 1,
        "l": 281.25
      },
      {
        "t": 9000,
        "d": 0,
        "l": 0
      },
      {
        "t": 9187.5,
        "d": 1,
        "l": 0
      },
      {
        "t": 9375,
        "d": 3,
        "l": 0
      },
      {
        "t": 9562.5,
        "d": 2,
        "l": 281.25
      },
      {
        "t": 9562.5,
        "d": 0,
        "l": 0,
        "p": {}
      },
      {
        "t": 9937.5,
        "d": 1,
        "l": 0
      },
      {
        "t": 10125,
        "d": 3,
        "l": 0
      },
      {
        "t": 10312.5,
        "d": 0,
        "l": 0
      },
      {
        "t": 10500,
        "d": 3,
        "l": 0
      },
      {
        "t": 10687.5,
        "d": 1,
        "l": 0
      },
      {
        "t": 10875,
        "d": 2,
        "l": 0
      },
      {
        "t": 11062.5,
        "d": 1,
        "l": 0
      },
      {
        "t": 11062.5,
        "d": 0,
        "l": 281.25
      },
      {
        "t": 11437.5,
        "d": 2,
        "l": 0
      },
      {
        "t": 11531.25,
        "d": 1,
        "l": 0
      },
      {
        "t": 11625,
        "d": 3,
        "l": 0
      },
      {
        "t": 11812.5,
        "d": 1,
        "l": 0
      },
      {
        "t": 12000,
        "d": 0,
        "l": 0
      },
      {
        "t": 12000,
        "d": 2,
        "l": 656.25
      },
      {
        "t": 12000,
        "d": 4,
        "l": 0,
        "p": {}
      },
      {
        "t": 12093.75,
        "d": 5,
        "l": 0,
        "p": {}
      },
      {
        "t": 12187.5,
        "d": 7,
        "l": 0,
        "p": {}
      },
      {
        "t": 12281.25,
        "d": 6,
        "l": 0,
        "p": {}
      },
      {
        "t": 12375,
        "d": 5,
        "l": 0,
        "p": {}
      },
      {
        "t": 12468.75,
        "d": 4,
        "l": 0,
        "p": {}
      },
      {
        "t": 12562.5,
        "d": 5,
        "l": 0,
        "p": {}
      },
      {
        "t": 12656.25,
        "d": 7,
        "l": 0,
        "p": {}
      },
      {
        "t": 12750,
        "d": 6,
        "l": 0,
        "p": {}
      },
      {
        "t": 12937.5,
        "d": 4,
        "l": 0,
        "p": {}
      },
      {
        "t": 13125,
        "d": 7,
        "l": 0,
        "p": {}
      },
      {
        "t": 13218.75,
        "d": 5,
        "l": 0,
        "p": {}
      },
      {
        "t": 13312.5,
        "d": 7,
        "l": 93.75,
        "p": {}
      },
      {
        "t": 13500,
        "d": 6,
        "l": 0,
        "p": {}
      },
      {
        "t": 13687.5,
        "d": 4,
        "l": 93.75,
        "p": {}
      },
      {
        "t": 13875,
        "d": 5,
        "l": 0,
        "p": {}
      },
      {
        "t": 13968.75,
        "d": 7,
        "l": 0,
        "p": {}
      },
      {
        "t": 14062.5,
        "d": 6,
        "l": 0,
        "p": {}
      },
      {
        "t": 14156.25,
        "d": 7,
        "l": 0,
        "p": {}
      },
      {
        "t": 14250,
        "d": 5,
        "l": 0,
        "p": {}
      },
      {
        "t": 14437.5,
        "d": 4,
        "l": 0,
        "p": {}
      },
      {
        "t": 14531.25,
        "d": 5,
        "l": 0,
        "p": {}
      },
      {
        "t": 14625,
        "d": 6,
        "l": 0,
        "p": {}
      },
      {
        "t": 14812.5,
        "d": 6,
        "l": 0,
        "p": {}
      },
      {
        "t": 14906.25,
        "d": 7,
        "l": 0,
        "p": {}
      },
      {
        "t": 15000,
        "d": 4,
        "l": 187.5,
        "p": {}
      },
      {
        "t": 15281.25,
        "d": 6,
        "l": 187.5,
        "p": {}
      },
      {
        "t": 15562.5,
        "d": 5,
        "l": 93.75,
        "p": {}
      },
      {
        "t": 15750,
        "d": 7,
        "l": 0,
        "p": {}
      },
      {
        "t": 15937.5,
        "d": 5,
        "l": 0,
        "p": {}
      },
      {
        "t": 16031.25,
        "d": 4,
        "l": 0,
        "p": {}
      },
      {
        "t": 16125,
        "d": 7,
        "l": 0,
        "p": {}
      },
      {
        "t": 16312.5,
        "d": 5,
        "l": 0,
        "p": {}
      },
      {
        "t": 16406.25,
        "d": 4,
        "l": 0,
        "p": {}
      },
      {
        "t": 16500,
        "d": 6,
        "l": 93.75,
        "p": {}
      },
      {
        "t": 16687.5,
        "d": 7,
        "l": 93.75,
        "p": {}
      },
      {
        "t": 16875,
        "d": 6,
        "l": 93.75,
        "p": {}
      },
      {
        "t": 17062.5,
        "d": 5,
        "l": 93.75,
        "p": {}
      },
      {
        "t": 17250,
        "d": 6,
        "l": 0,
        "p": {}
      },
      {
        "t": 17437.5,
        "d": 6,
        "l": 0,
        "p": {}
      },
      {
        "t": 17531.25,
        "d": 5,
        "l": 0,
        "p": {}
      },
      {
        "t": 17625,
        "d": 4,
        "l": 0,
        "p": {}
      },
      {
        "t": 17812.5,
        "d": 7,
        "l": 93.75,
        "p": {}
      },
      {
        "t": 18000,
        "d": 5,
        "l": 281.25,
        "p": {}
      },
      {
        "t": 18000,
        "d": 0,
        "l": 0
      },
      {
        "t": 18187.5,
        "d": 3,
        "l": 0
      },
      {
        "t": 18281.25,
        "d": 2,
        "l": 0
      },
      {
        "t": 18375,
        "d": 1,
        "l": 0
      },
      {
        "t": 18468.75,
        "d": 0,
        "l": 0
      },
      {
        "t": 18562.5,
        "d": 1,
        "l": 0
      },
      {
        "t": 18656.25,
        "d": 3,
        "l": 0
      },
      {
        "t": 18750,
        "d": 2,
        "l": 0
      },
      {
        "t": 18937.5,
        "d": 0,
        "l": 0
      },
      {
        "t": 19125,
        "d": 3,
        "l": 0
      },
      {
        "t": 19218.75,
        "d": 1,
        "l": 0
      },
      {
        "t": 19312.5,
        "d": 3,
        "l": 93.75
      },
      {
        "t": 19500,
        "d": 2,
        "l": 0
      },
      {
        "t": 19687.5,
        "d": 0,
        "l": 93.75
      },
      {
        "t": 19875,
        "d": 1,
        "l": 0
      },
      {
        "t": 19968.75,
        "d": 3,
        "l": 0
      },
      {
        "t": 20062.5,
        "d": 2,
        "l": 0
      },
      {
        "t": 20156.25,
        "d": 3,
        "l": 0
      },
      {
        "t": 20250,
        "d": 1,
        "l": 0
      },
      {
        "t": 20437.5,
        "d": 0,
        "l": 0
      },
      {
        "t": 20531.25,
        "d": 1,
        "l": 0
      },
      {
        "t": 20625,
        "d": 2,
        "l": 0
      },
      {
        "t": 20812.5,
        "d": 2,
        "l": 0
      },
      {
        "t": 20906.25,
        "d": 3,
        "l": 0
      },
      {
        "t": 21000,
        "d": 0,
        "l": 187.5
      },
      {
        "t": 21281.25,
        "d": 2,
        "l": 187.5
      },
      {
        "t": 21562.5,
        "d": 1,
        "l": 93.75
      },
      {
        "t": 21750,
        "d": 3,
        "l": 0
      },
      {
        "t": 21937.5,
        "d": 1,
        "l": 0
      },
      {
        "t": 22031.25,
        "d": 0,
        "l": 0
      },
      {
        "t": 22125,
        "d": 3,
        "l": 0
      },
      {
        "t": 22312.5,
        "d": 1,
        "l": 0
      },
      {
        "t": 22406.25,
        "d": 0,
        "l": 0
      },
      {
        "t": 22500,
        "d": 2,
        "l": 93.75
      },
      {
        "t": 22687.5,
        "d": 3,
        "l": 93.75
      },
      {
        "t": 22875,
        "d": 2,
        "l": 93.75
      },
      {
        "t": 23062.5,
        "d": 1,
        "l": 93.75
      },
      {
        "t": 23250,
        "d": 2,
        "l": 0
      },
      {
        "t": 23437.5,
        "d": 2,
        "l": 0
      },
      {
        "t": 23531.25,
        "d": 1,
        "l": 0
      },
      {
        "t": 23625,
        "d": 0,
        "l": 0
      },
      {
        "t": 23812.5,
        "d": 3,
        "l": 93.75
      },
      {
        "t": 24000,
        "d": 1,
        "l": 281.25
      },
      {
        "t": 24187.5,
        "d": 4,
        "l": 93.75,
        "p": {}
      },
      {
        "t": 24562.5,
        "d": 4,
        "l": 93.75,
        "p": {}
      },
      {
        "t": 24937.5,
        "d": 4,
        "l": 0,
        "p": {}
      },
      {
        "t": 25125,
        "d": 5,
        "l": 0,
        "p": {}
      },
      {
        "t": 25312.5,
        "d": 6,
        "l": 93.75,
        "p": {}
      },
      {
        "t": 25687.5,
        "d": 4,
        "l": 93.75,
        "p": {}
      },
      {
        "t": 26062.5,
        "d": 5,
        "l": 0,
        "p": {}
      },
      {
        "t": 26156.25,
        "d": 4,
        "l": 0,
        "p": {}
      },
      {
        "t": 26437.5,
        "d": 4,
        "l": 93.75,
        "p": {}
      },
      {
        "t": 26625,
        "d": 5,
        "l": 0,
        "p": {}
      },
      {
        "t": 26812.5,
        "d": 6,
        "l": 0,
        "p": {}
      },
      {
        "t": 26906.25,
        "d": 7,
        "l": 0,
        "p": {}
      },
      {
        "t": 27000,
        "d": 4,
        "l": 93.75,
        "p": {}
      },
      {
        "t": 27187.5,
        "d": 0,
        "l": 93.75
      },
      {
        "t": 27562.5,
        "d": 0,
        "l": 93.75,
        "p": {}
      },
      {
        "t": 27937.5,
        "d": 0,
        "l": 0
      },
      {
        "t": 28125,
        "d": 1,
        "l": 0
      },
      {
        "t": 28312.5,
        "d": 2,
        "l": 93.75
      },
      {
        "t": 28687.5,
        "d": 1,
        "l": 93.75
      },
      {
        "t": 29062.5,
        "d": 3,
        "l": 0
      },
      {
        "t": 29156.25,
        "d": 1,
        "l": 0
      },
      {
        "t": 29437.5,
        "d": 0,
        "l": 93.75
      },
      {
        "t": 29625,
        "d": 1,
        "l": 0
      },
      {
        "t": 29812.5,
        "d": 2,
        "l": 0
      },
      {
        "t": 29906.25,
        "d": 3,
        "l": 0
      },
      {
        "t": 30000,
        "d": 0,
        "l": 1031.25,
        "p": {}
      },
      {
        "t": 30000,
        "d": 4,
        "l": 0,
        "p": {}
      },
      {
        "t": 30187.5,
        "d": 6,
        "l": 0,
        "p": {}
      },
      {
        "t": 30375,
        "d": 7,
        "l": 0,
        "p": {}
      },
      {
        "t": 30562.5,
        "d": 5,
        "l": 0,
        "p": {}
      },
      {
        "t": 30750,
        "d": 5,
        "l": 93.75,
        "p": {}
      },
      {
        "t": 31031.25,
        "d": 4,
        "l": 0,
        "p": {}
      },
      {
        "t": 31125,
        "d": 2,
        "l": 281.25,
        "p": {}
      },
      {
        "t": 31312.5,
        "d": 7,
        "l": 0,
        "p": {}
      },
      {
        "t": 31500,
        "d": 3,
        "l": 1031.25,
        "p": {}
      },
      {
        "t": 31500,
        "d": 5,
        "l": 0,
        "p": {}
      },
      {
        "t": 31687.5,
        "d": 6,
        "l": 0,
        "p": {}
      },
      {
        "t": 31781.25,
        "d": 5,
        "l": 0,
        "p": {}
      },
      {
        "t": 31875,
        "d": 4,
        "l": 93.75,
        "p": {}
      },
      {
        "t": 32062.5,
        "d": 5,
        "l": 0,
        "p": {}
      },
      {
        "t": 32250,
        "d": 4,
        "l": 93.75,
        "p": {}
      },
      {
        "t": 32437.5,
        "d": 5,
        "l": 0,
        "p": {}
      },
      {
        "t": 32625,
        "d": 2,
        "l": 281.25,
        "p": {}
      },
      {
        "t": 32625,
        "d": 7,
        "l": 93.75,
        "p": {}
      },
      {
        "t": 32812.5,
        "d": 6,
        "l": 93.75,
        "p": {}
      },
      {
        "t": 33000,
        "d": 1,
        "l": 1031.25,
        "p": {}
      },
      {
        "t": 33000,
        "d": 4,
        "l": 0,
        "p": {}
      },
      {
        "t": 33093.75,
        "d": 5,
        "l": 0,
        "p": {}
      },
      {
        "t": 33187.5,
        "d": 4,
        "l": 0,
        "p": {}
      },
      {
        "t": 33281.25,
        "d": 6,
        "l": 0,
        "p": {}
      },
      {
        "t": 33375,
        "d": 7,
        "l": 93.75,
        "p": {}
      },
      {
        "t": 33750,
        "d": 4,
        "l": 0,
        "p": {}
      },
      {
        "t": 33843.75,
        "d": 5,
        "l": 0
      },
      {
        "t": 33937.5,
        "d": 4,
        "l": 0
      },
      {
        "t": 34031.25,
        "d": 6,
        "l": 0
      },
      {
        "t": 34125,
        "d": 0,
        "l": 281.25,
        "p": {}
      },
      {
        "t": 34125,
        "d": 7,
        "l": 93.75,
        "p": {}
      },
      {
        "t": 34312.5,
        "d": 6,
        "l": 0,
        "p": {}
      },
      {
        "t": 34406.25,
        "d": 5,
        "l": 0,
        "p": {}
      },
      {
        "t": 34500,
        "d": 2,
        "l": 93.75,
        "p": {}
      },
      {
        "t": 34500,
        "d": 4,
        "l": 93.75,
        "p": {}
      },
      {
        "t": 34687.5,
        "d": 1,
        "l": 0,
        "p": {}
      },
      {
        "t": 34687.5,
        "d": 6,
        "l": 93.75,
        "p": {}
      },
      {
        "t": 34875,
        "d": 2,
        "l": 93.75,
        "p": {}
      },
      {
        "t": 34875,
        "d": 4,
        "l": 93.75,
        "p": {}
      },
      {
        "t": 35062.5,
        "d": 3,
        "l": 0,
        "p": {}
      },
      {
        "t": 35062.5,
        "d": 7,
        "l": 0,
        "p": {}
      },
      {
        "t": 35156.25,
        "d": 1,
        "l": 0,
        "p": {}
      },
      {
        "t": 35156.25,
        "d": 5,
        "l": 0,
        "p": {}
      },
      {
        "t": 35250,
        "d": 0,
        "l": 281.25,
        "p": {}
      },
      {
        "t": 35250,
        "d": 6,
        "l": 93.75,
        "p": {}
      },
      {
        "t": 35437.5,
        "d": 4,
        "l": 93.75,
        "p": {}
      },
      {
        "t": 35625,
        "d": 2,
        "l": 281.25,
        "p": {}
      },
      {
        "t": 35625,
        "d": 5,
        "l": 0,
        "p": {}
      },
      {
        "t": 35718.75,
        "d": 6,
        "l": 0,
        "p": {}
      },
      {
        "t": 35812.5,
        "d": 7,
        "l": 0,
        "p": {}
      },
      {
        "t": 35906.25,
        "d": 5,
        "l": 0,
        "p": {}
      },
      {
        "t": 36000,
        "d": 4,
        "l": 1031.25
      },
      {
        "t": 36000,
        "d": 0,
        "l": 0
      },
      {
        "t": 36187.5,
        "d": 2,
        "l": 0
      },
      {
        "t": 36375,
        "d": 3,
        "l": 0
      },
      {
        "t": 36562.5,
        "d": 1,
        "l": 0
      },
      {
        "t": 36750,
        "d": 1,
        "l": 93.75,
        "p": {}
      },
      {
        "t": 37031.25,
        "d": 0,
        "l": 0
      },
      {
        "t": 37125,
        "d": 6,
        "l": 281.25
      },
      {
        "t": 37312.5,
        "d": 3,
        "l": 0
      },
      {
        "t": 37500,
        "d": 7,
        "l": 1031.25
      },
      {
        "t": 37500,
        "d": 1,
        "l": 0
      },
      {
        "t": 37687.5,
        "d": 2,
        "l": 0
      },
      {
        "t": 37781.25,
        "d": 1,
        "l": 0
      },
      {
        "t": 37875,
        "d": 0,
        "l": 93.75
      },
      {
        "t": 38062.5,
        "d": 1,
        "l": 0
      },
      {
        "t": 38250,
        "d": 0,
        "l": 93.75
      },
      {
        "t": 38437.5,
        "d": 1,
        "l": 0
      },
      {
        "t": 38625,
        "d": 6,
        "l": 281.25
      },
      {
        "t": 38625,
        "d": 3,
        "l": 93.75
      },
      {
        "t": 38812.5,
        "d": 2,
        "l": 93.75
      },
      {
        "t": 39000,
        "d": 5,
        "l": 1031.25
      },
      {
        "t": 39000,
        "d": 0,
        "l": 0
      },
      {
        "t": 39093.75,
        "d": 1,
        "l": 0
      },
      {
        "t": 39187.5,
        "d": 0,
        "l": 0
      },
      {
        "t": 39281.25,
        "d": 2,
        "l": 0
      },
      {
        "t": 39375,
        "d": 3,
        "l": 93.75
      },
      {
        "t": 39750,
        "d": 0,
        "l": 0
      },
      {
        "t": 39937.5,
        "d": 0,
        "l": 0
      },
      {
        "t": 40031.25,
        "d": 2,
        "l": 0
      },
      {
        "t": 40125,
        "d": 4,
        "l": 281.25
      },
      {
        "t": 40125,
        "d": 3,
        "l": 93.75
      },
      {
        "t": 40312.5,
        "d": 2,
        "l": 0
      },
      {
        "t": 40406.25,
        "d": 1,
        "l": 0
      },
      {
        "t": 40500,
        "d": 6,
        "l": 93.75
      },
      {
        "t": 40500,
        "d": 0,
        "l": 93.75
      },
      {
        "t": 40687.5,
        "d": 2,
        "l": 93.75
      },
      {
        "t": 40875,
        "d": 6,
        "l": 93.75
      },
      {
        "t": 40875,
        "d": 0,
        "l": 93.75
      },
      {
        "t": 41062.5,
        "d": 3,
        "l": 0
      },
      {
        "t": 41156.25,
        "d": 1,
        "l": 0
      },
      {
        "t": 41250,
        "d": 6,
        "l": 93.75,
        "p": {}
      },
      {
        "t": 41250,
        "d": 2,
        "l": 93.75
      },
      {
        "t": 41437.5,
        "d": 0,
        "l": 93.75
      },
      {
        "t": 41625,
        "d": 6,
        "l": 93.75,
        "p": {}
      },
      {
        "t": 41625,
        "d": 1,
        "l": 0
      },
      {
        "t": 41812.5,
        "d": 3,
        "l": 0
      },
      {
        "t": 41906.25,
        "d": 1,
        "l": 0
      },
      {
        "t": 42000,
        "d": 0,
        "l": 1031.25
      },
      {
        "t": 42000,
        "d": 6,
        "l": 281.25,
        "p": {}
      },
      {
        "t": 42375,
        "d": 4,
        "l": 0,
        "p": {}
      },
      {
        "t": 42468.75,
        "d": 5,
        "l": 0,
        "p": {}
      },
      {
        "t": 42562.5,
        "d": 6,
        "l": 187.5,
        "p": {}
      },
      {
        "t": 42937.5,
        "d": 6,
        "l": 0,
        "p": {}
      },
      {
        "t": 43125,
        "d": 7,
        "l": 93.75,
        "p": {}
      },
      {
        "t": 43312.5,
        "d": 5,
        "l": 0,
        "p": {}
      },
      {
        "t": 43500,
        "d": 6,
        "l": 93.75,
        "p": {}
      },
      {
        "t": 43687.5,
        "d": 4,
        "l": 0,
        "p": {}
      },
      {
        "t": 43781.25,
        "d": 5,
        "l": 0,
        "p": {}
      },
      {
        "t": 43875,
        "d": 7,
        "l": 93.75,
        "p": {}
      },
      {
        "t": 44062.5,
        "d": 5,
        "l": 0,
        "p": {}
      },
      {
        "t": 44250,
        "d": 6,
        "l": 93.75,
        "p": {}
      },
      {
        "t": 44437.5,
        "d": 4,
        "l": 0,
        "p": {}
      },
      {
        "t": 44531.25,
        "d": 5,
        "l": 0,
        "p": {}
      },
      {
        "t": 44625,
        "d": 7,
        "l": 93.75,
        "p": {}
      },
      {
        "t": 44812.5,
        "d": 5,
        "l": 93.75,
        "p": {}
      },
      {
        "t": 45000,
        "d": 4,
        "l": 93.75,
        "p": {}
      },
      {
        "t": 45187.5,
        "d": 5,
        "l": 93.75,
        "p": {}
      },
      {
        "t": 45375,
        "d": 4,
        "l": 93.75,
        "p": {}
      },
      {
        "t": 45562.5,
        "d": 6,
        "l": 0,
        "p": {}
      },
      {
        "t": 45656.25,
        "d": 5,
        "l": 0,
        "p": {}
      },
      {
        "t": 45750,
        "d": 4,
        "l": 93.75,
        "p": {}
      },
      {
        "t": 45937.5,
        "d": 5,
        "l": 0,
        "p": {}
      },
      {
        "t": 46031.25,
        "d": 7,
        "l": 0,
        "p": {}
      },
      {
        "t": 46125,
        "d": 6,
        "l": 0,
        "p": {}
      },
      {
        "t": 46218.75,
        "d": 5,
        "l": 0,
        "p": {}
      },
      {
        "t": 46312.5,
        "d": 4,
        "l": 0,
        "p": {}
      },
      {
        "t": 46406.25,
        "d": 5,
        "l": 0,
        "p": {}
      },
      {
        "t": 46500,
        "d": 7,
        "l": 0,
        "p": {}
      },
      {
        "t": 46593.75,
        "d": 5,
        "l": 0,
        "p": {}
      },
      {
        "t": 46687.5,
        "d": 7,
        "l": 0,
        "p": {}
      },
      {
        "t": 46781.25,
        "d": 5,
        "l": 0,
        "p": {}
      },
      {
        "t": 46875,
        "d": 7,
        "l": 93.75,
        "p": {}
      },
      {
        "t": 47062.5,
        "d": 4,
        "l": 281.25,
        "p": {}
      },
      {
        "t": 47437.5,
        "d": 5,
        "l": 0,
        "p": {}
      },
      {
        "t": 47625,
        "d": 7,
        "l": 93.75,
        "p": {}
      },
      {
        "t": 47812.5,
        "d": 6,
        "l": 93.75,
        "p": {}
      },
      {
        "t": 48000,
        "d": 4,
        "l": 281.25,
        "p": {}
      },
      {
        "t": 48000,
        "d": 2,
        "l": 281.25
      },
      {
        "t": 48375,
        "d": 5,
        "l": 281.25,
        "p": {}
      },
      {
        "t": 48375,
        "d": 0,
        "l": 0
      },
      {
        "t": 48468.75,
        "d": 1,
        "l": 0
      },
      {
        "t": 48562.5,
        "d": 2,
        "l": 187.5
      },
      {
        "t": 48937.5,
        "d": 2,
        "l": 0
      },
      {
        "t": 49125,
        "d": 3,
        "l": 93.75
      },
      {
        "t": 49312.5,
        "d": 1,
        "l": 0
      },
      {
        "t": 49500,
        "d": 2,
        "l": 93.75
      },
      {
        "t": 49687.5,
        "d": 0,
        "l": 0
      },
      {
        "t": 49781.25,
        "d": 1,
        "l": 0
      },
      {
        "t": 49875,
        "d": 3,
        "l": 93.75
      },
      {
        "t": 50062.5,
        "d": 1,
        "l": 0
      },
      {
        "t": 50250,
        "d": 2,
        "l": 93.75
      },
      {
        "t": 50437.5,
        "d": 0,
        "l": 0
      },
      {
        "t": 50531.25,
        "d": 1,
        "l": 0
      },
      {
        "t": 50625,
        "d": 3,
        "l": 93.75
      },
      {
        "t": 50812.5,
        "d": 1,
        "l": 93.75
      },
      {
        "t": 51000,
        "d": 0,
        "l": 93.75
      },
      {
        "t": 51187.5,
        "d": 1,
        "l": 93.75
      },
      {
        "t": 51375,
        "d": 0,
        "l": 93.75
      },
      {
        "t": 51562.5,
        "d": 2,
        "l": 0
      },
      {
        "t": 51656.25,
        "d": 1,
        "l": 0
      },
      {
        "t": 51750,
        "d": 0,
        "l": 93.75
      },
      {
        "t": 51937.5,
        "d": 1,
        "l": 0
      },
      {
        "t": 52031.25,
        "d": 3,
        "l": 0
      },
      {
        "t": 52125,
        "d": 2,
        "l": 0
      },
      {
        "t": 52218.75,
        "d": 1,
        "l": 0
      },
      {
        "t": 52312.5,
        "d": 0,
        "l": 0
      },
      {
        "t": 52406.25,
        "d": 1,
        "l": 0
      },
      {
        "t": 52500,
        "d": 3,
        "l": 0
      },
      {
        "t": 52593.75,
        "d": 1,
        "l": 0
      },
      {
        "t": 52687.5,
        "d": 3,
        "l": 0
      },
      {
        "t": 52781.25,
        "d": 1,
        "l": 0
      },
      {
        "t": 52875,
        "d": 3,
        "l": 93.75
      },
      {
        "t": 53062.5,
        "d": 0,
        "l": 281.25
      },
      {
        "t": 53437.5,
        "d": 1,
        "l": 0
      },
      {
        "t": 53625,
        "d": 3,
        "l": 93.75
      },
      {
        "t": 53812.5,
        "d": 2,
        "l": 93.75
      },
      {
        "t": 54000,
        "d": 0,
        "l": 281.25
      },
      {
        "t": 54375,
        "d": 1,
        "l": 281.25
      }
    ]
  },
  "generatedBy": "FreyaFennec_Funkers ALPHA - FNF v0.5.3 "
}